rtl/bird_deterrent_pwm.v
// Ultrasonic PWM generator for bird deterrence
//
// tone_val is a half-period divisor:
//   tone_val = 333 → half-period = 333 cycles @ 12MHz → full period = 666 → ~18kHz (max, safe ceiling)
//   tone_val = 353 → half-period = 353 cycles @ 12MHz → full period = 706 → ~17kHz (min)
//
// When enable=0, speaker_out is held low (silent).
// When enable=1, speaker_out toggles at the rate set by tone_val.
module bird_deterrent_pwm (
    input            clk,
    input  [15:0]    tone_val,
    input            enable,
    output reg       speaker_out
);
    reg [15:0] counter;

    always @(posedge clk) begin
        if (!enable) begin
            counter     <= 16'd0;
            speaker_out <= 1'b0;
        end else begin
            if (counter == 16'd0) begin
                counter     <= tone_val;   // reload
                speaker_out <= ~speaker_out; // toggle = one half-cycle done
            end else begin
                counter <= counter - 1'b1;
            end
        end
    end
endmodule

sim/tb_bird_deterrent_pwm.v
// Testbench: bird_deterrent_pwm
//
// What this tests:
//   1. speaker_out stays LOW when enable=0
//   2. speaker_out toggles at correct half-period when enable=1
//      Expected half-period = tone_val clock cycles
//      At tone_val=353 → 353 cycles per toggle → ~17kHz @ 12MHz
//
// Run: make sim_pwm (from sim/ directory)
// View: gtkwave tb_bird_deterrent_pwm.vcd
`timescale 1ns/1ps

module tb_bird_deterrent_pwm;

    reg        clk;
    reg        enable;
    reg [15:0] tone_val;
    wire       speaker_out;

    // DUT
    bird_deterrent_pwm dut (
        .clk        (clk),
        .tone_val   (tone_val),
        .enable     (enable),
        .speaker_out(speaker_out)
    );

    // 12MHz clock: period = 83.3ns → half = ~41ns
    initial clk = 0;
    always #41 clk = ~clk;

    // Track toggle times to verify half-period
    integer last_toggle_time;
    integer half_period_cycles;

    initial last_toggle_time = 0;

    always @(posedge speaker_out or negedge speaker_out) begin
        if (last_toggle_time != 0) begin
            half_period_cycles = ($time - last_toggle_time) / 82; // ~82ns per cycle
            $display("[%0t ns] Toggle — half-period = %0d cycles (expected ~%0d)",
                     $time, half_period_cycles, tone_val);
        end
        last_toggle_time = $time;
    end

    integer i;

    initial begin
        $dumpfile("tb_bird_deterrent_pwm.vcd");
        $dumpvars(0, tb_bird_deterrent_pwm);

        // --- Test 1: Silent when disabled ---
        enable   = 0;
        tone_val = 16'd353;
        repeat(500) @(posedge clk);

        if (speaker_out !== 1'b0)
            $display("FAIL Test1: speaker active while enable=0");
        else
            $display("PASS Test1: speaker silent when disabled");

        // --- Test 2: Toggle at tone_val=353 (~17kHz) ---
        enable = 1;
        // Wait for 6 full cycles (6 * 2 * 353 = 4236 clocks)
        repeat(4500) @(posedge clk);
        $display("PASS Test2: 17kHz sweep — check waveform for period");

        // --- Test 3: Reload with tone_val=333 (~18kHz ceiling) ---
        tone_val = 16'd333;
        repeat(4000) @(posedge clk);
        $display("PASS Test3: 18kHz sweep — check waveform for period");

        // --- Test 4: Disable mid-sweep, output should go low ---
        enable = 0;
        repeat(100) @(posedge clk);
        if (speaker_out !== 1'b0)
            $display("FAIL Test4: speaker not silenced on disable");
        else
            $display("PASS Test4: speaker silenced on disable");

        $display("--- Simulation complete ---");
        $finish;
    end

endmodule

sim/tb_bird_deterrent_pwm.vcd
$date
	Tue Apr 28 22:35:47 2026
$end
$version
	Icarus Verilog
$end
$timescale
	1ps
$end
$scope module tb_bird_deterrent_pwm $end
$var wire 1 ! speaker_out $end
$var reg 1 " clk $end
$var reg 1 # enable $end
$var reg 16 $ tone_val [15:0] $end
$var integer 32 % half_period_cycles [31:0] $end
$var integer 32 & last_toggle_time [31:0] $end
$scope module dut $end
$var wire 1 " clk $end
$var wire 1 # enable $end
$var wire 16 ' tone_val [15:0] $end
$var reg 16 ( counter [15:0] $end
$var reg 1 ! speaker_out $end
$upscope $end
$upscope $end
$enddefinitions $end
#0
$dumpvars
bx (
b101100001 '
b0 &
bx %
b101100001 $
0#
0"
x!
$end
#41000
b101001 &
0!
b0 (
1"
#82000
0"
#123000
1"
#164000
0"
#205000
1"
#246000
0"
#287000
1"
#328000
0"
#369000
1"
#410000
0"
#451000
1"
#492000
0"
#533000
1"
#574000
0"
#615000
1"
#656000
0"
#697000
1"
#738000
0"
#779000
1"
#820000
0"
#861000
1"
#902000
0"
#943000
1"
#984000
0"
#1025000
1"
#1066000
0"
#1107000
1"
#1148000
0"
#1189000
1"
#1230000
0"
#1271000
1"
#1312000
0"
#1353000
1"
#1394000
0"
#1435000
1"
#1476000
0"
#1517000
1"
#1558000
0"
#1599000
1"
#1640000
0"
#1681000
1"
#1722000
0"
#1763000
1"
#1804000
0"
#1845000
1"
#1886000
0"
#1927000
1"
#1968000
0"
#2009000
1"
#2050000
0"
#2091000
1"
#2132000
0"
#2173000
1"
#2214000
0"
#2255000
1"
#2296000
0"
#2337000
1"
#2378000
0"
#2419000
1"
#2460000
0"
#2501000
1"
#2542000
0"
#2583000
1"
#2624000
0"
#2665000
1"
#2706000
0"
#2747000
1"
#2788000
0"
#2829000
1"
#2870000
0"
#2911000
1"
#2952000
0"
#2993000
1"
#3034000
0"
#3075000
1"
#3116000
0"
#3157000
1"
#3198000
0"
#3239000
1"
#3280000
0"
#3321000
1"
#3362000
0"
#3403000
1"
#3444000
0"
#3485000
1"
#3526000
0"
#3567000
1"
#3608000
0"
#3649000
1"
#3690000
0"
#3731000
1"
#3772000
0"
#3813000
1"
#3854000
0"
#3895000
1"
#3936000
0"
#3977000
1"
#4018000
0"
#4059000
1"
#4100000
0"
#4141000
1"
#4182000
0"
#4223000
1"
#4264000
0"
#4305000
1"
#4346000
0"
#4387000
1"
#4428000
0"
#4469000
1"
#4510000
0"
#4551000
1"
#4592000
0"
#4633000
1"
#4674000
0"
#4715000
1"
#4756000
0"
#4797000
1"
#4838000
0"
#4879000
1"
#4920000
0"
#4961000
1"
#5002000
0"
#5043000
1"
#5084000
0"
#5125000
1"
#5166000
0"
#5207000
1"
#5248000
0"
#5289000
1"
#5330000
0"
#5371000
1"
#5412000
0"
#5453000
1"
#5494000
0"
#5535000
1"
#5576000
0"
#5617000
1"
#5658000
0"
#5699000
1"
#5740000
0"
#5781000
1"
#5822000
0"
#5863000
1"
#5904000
0"
#5945000
1"
#5986000
0"
#6027000
1"
#6068000
0"
#6109000
1"
#6150000
0"
#6191000
1"
#6232000
0"
#6273000
1"
#6314000
0"
#6355000
1"
#6396000
0"
#6437000
1"
#6478000
0"
#6519000
1"
#6560000
0"
#6601000
1"
#6642000
0"
#6683000
1"
#6724000
0"
#6765000
1"
#6806000
0"
#6847000
1"
#6888000
0"
#6929000
1"
#6970000
0"
#7011000
1"
#7052000
0"
#7093000
1"
#7134000
0"
#7175000
1"
#7216000
0"
#7257000
1"
#7298000
0"
#7339000
1"
#7380000
0"
#7421000
1"
#7462000
0"
#7503000
1"
#7544000
0"
#7585000
1"
#7626000
0"
#7667000
1"
#7708000
0"
#7749000
1"
#7790000
0"
#7831000
1"
#7872000
0"
#7913000
1"
#7954000
0"
#7995000
1"
#8036000
0"
#8077000
1"
#8118000
0"
#8159000
1"
#8200000
0"
#8241000
1"
#8282000
0"
#8323000
1"
#8364000
0"
#8405000
1"
#8446000
0"
#8487000
1"
#8528000
0"
#8569000
1"
#8610000
0"
#8651000
1"
#8692000
0"
#8733000
1"
#8774000
0"
#8815000
1"
#8856000
0"
#8897000
1"
#8938000
0"
#8979000
1"
#9020000
0"
#9061000
1"
#9102000
0"
#9143000
1"
#9184000
0"
#9225000
1"
#9266000
0"
#9307000
1"
#9348000
0"
#9389000
1"
#9430000
0"
#9471000
1"
#9512000
0"
#9553000
1"
#9594000
0"
#9635000
1"
#9676000
0"
#9717000
1"
#9758000
0"
#9799000
1"
#9840000
0"
#9881000
1"
#9922000
0"
#9963000
1"
#10004000
0"
#10045000
1"
#10086000
0"
#10127000
1"
#10168000
0"
#10209000
1"
#10250000
0"
#10291000
1"
#10332000
0"
#10373000
1"
#10414000
0"
#10455000
1"
#10496000
0"
#10537000
1"
#10578000
0"
#10619000
1"
#10660000
0"
#10701000
1"
#10742000
0"
#10783000
1"
#10824000
0"
#10865000
1"
#10906000
0"
#10947000
1"
#10988000
0"
#11029000
1"
#11070000
0"
#11111000
1"
#11152000
0"
#11193000
1"
#11234000
0"
#11275000
1"
#11316000
0"
#11357000
1"
#11398000
0"
#11439000
1"
#11480000
0"
#11521000
1"
#11562000
0"
#11603000
1"
#11644000
0"
#11685000
1"
#11726000
0"
#11767000
1"
#11808000
0"
#11849000
1"
#11890000
0"
#11931000
1"
#11972000
0"
#12013000
1"
#12054000
0"
#12095000
1"
#12136000
0"
#12177000
1"
#12218000
0"
#12259000
1"
#12300000
0"
#12341000
1"
#12382000
0"
#12423000
1"
#12464000
0"
#12505000
1"
#12546000
0"
#12587000
1"
#12628000
0"
#12669000
1"
#12710000
0"
#12751000
1"
#12792000
0"
#12833000
1"
#12874000
0"
#12915000
1"
#12956000
0"
#12997000
1"
#13038000
0"
#13079000
1"
#13120000
0"
#13161000
1"
#13202000
0"
#13243000
1"
#13284000
0"
#13325000
1"
#13366000
0"
#13407000
1"
#13448000
0"
#13489000
1"
#13530000
0"
#13571000
1"
#13612000
0"
#13653000
1"
#13694000
0"
#13735000
1"
#13776000
0"
#13817000
1"
#13858000
0"
#13899000
1"
#13940000
0"
#13981000
1"
#14022000
0"
#14063000
1"
#14104000
0"
#14145000
1"
#14186000
0"
#14227000
1"
#14268000
0"
#14309000
1"
#14350000
0"
#14391000
1"
#14432000
0"
#14473000
1"
#14514000
0"
#14555000
1"
#14596000
0"
#14637000
1"
#14678000
0"
#14719000
1"
#14760000
0"
#14801000
1"
#14842000
0"
#14883000
1"
#14924000
0"
#14965000
1"
#15006000
0"
#15047000
1"
#15088000
0"
#15129000
1"
#15170000
0"
#15211000
1"
#15252000
0"
#15293000
1"
#15334000
0"
#15375000
1"
#15416000
0"
#15457000
1"
#15498000
0"
#15539000
1"
#15580000
0"
#15621000
1"
#15662000
0"
#15703000
1"
#15744000
0"
#15785000
1"
#15826000
0"
#15867000
1"
#15908000
0"
#15949000
1"
#15990000
0"
#16031000
1"
#16072000
0"
#16113000
1"
#16154000
0"
#16195000
1"
#16236000
0"
#16277000
1"
#16318000
0"
#16359000
1"
#16400000
0"
#16441000
1"
#16482000
0"
#16523000
1"
#16564000
0"
#16605000
1"
#16646000
0"
#16687000
1"
#16728000
0"
#16769000
1"
#16810000
0"
#16851000
1"
#16892000
0"
#16933000
1"
#16974000
0"
#17015000
1"
#17056000
0"
#17097000
1"
#17138000
0"
#17179000
1"
#17220000
0"
#17261000
1"
#17302000
0"
#17343000
1"
#17384000
0"
#17425000
1"
#17466000
0"
#17507000
1"
#17548000
0"
#17589000
1"
#17630000
0"
#17671000
1"
#17712000
0"
#17753000
1"
#17794000
0"
#17835000
1"
#17876000
0"
#17917000
1"
#17958000
0"
#17999000
1"
#18040000
0"
#18081000
1"
#18122000
0"
#18163000
1"
#18204000
0"
#18245000
1"
#18286000
0"
#18327000
1"
#18368000
0"
#18409000
1"
#18450000
0"
#18491000
1"
#18532000
0"
#18573000
1"
#18614000
0"
#18655000
1"
#18696000
0"
#18737000
1"
#18778000
0"
#18819000
1"
#18860000
0"
#18901000
1"
#18942000
0"
#18983000
1"
#19024000
0"
#19065000
1"
#19106000
0"
#19147000
1"
#19188000
0"
#19229000
1"
#19270000
0"
#19311000
1"
#19352000
0"
#19393000
1"
#19434000
0"
#19475000
1"
#19516000
0"
#19557000
1"
#19598000
0"
#19639000
1"
#19680000
0"
#19721000
1"
#19762000
0"
#19803000
1"
#19844000
0"
#19885000
1"
#19926000
0"
#19967000
1"
#20008000
0"
#20049000
1"
#20090000
0"
#20131000
1"
#20172000
0"
#20213000
1"
#20254000
0"
#20295000
1"
#20336000
0"
#20377000
1"
#20418000
0"
#20459000
1"
#20500000
0"
#20541000
1"
#20582000
0"
#20623000
1"
#20664000
0"
#20705000
1"
#20746000
0"
#20787000
1"
#20828000
0"
#20869000
1"
#20910000
0"
#20951000
1"
#20992000
0"
#21033000
1"
#21074000
0"
#21115000
1"
#21156000
0"
#21197000
1"
#21238000
0"
#21279000
1"
#21320000
0"
#21361000
1"
#21402000
0"
#21443000
1"
#21484000
0"
#21525000
1"
#21566000
0"
#21607000
1"
#21648000
0"
#21689000
1"
#21730000
0"
#21771000
1"
#21812000
0"
#21853000
1"
#21894000
0"
#21935000
1"
#21976000
0"
#22017000
1"
#22058000
0"
#22099000
1"
#22140000
0"
#22181000
1"
#22222000
0"
#22263000
1"
#22304000
0"
#22345000
1"
#22386000
0"
#22427000
1"
#22468000
0"
#22509000
1"
#22550000
0"
#22591000
1"
#22632000
0"
#22673000
1"
#22714000
0"
#22755000
1"
#22796000
0"
#22837000
1"
#22878000
0"
#22919000
1"
#22960000
0"
#23001000
1"
#23042000
0"
#23083000
1"
#23124000
0"
#23165000
1"
#23206000
0"
#23247000
1"
#23288000
0"
#23329000
1"
#23370000
0"
#23411000
1"
#23452000
0"
#23493000
1"
#23534000
0"
#23575000
1"
#23616000
0"
#23657000
1"
#23698000
0"
#23739000
1"
#23780000
0"
#23821000
1"
#23862000
0"
#23903000
1"
#23944000
0"
#23985000
1"
#24026000
0"
#24067000
1"
#24108000
0"
#24149000
1"
#24190000
0"
#24231000
1"
#24272000
0"
#24313000
1"
#24354000
0"
#24395000
1"
#24436000
0"
#24477000
1"
#24518000
0"
#24559000
1"
#24600000
0"
#24641000
1"
#24682000
0"
#24723000
1"
#24764000
0"
#24805000
1"
#24846000
0"
#24887000
1"
#24928000
0"
#24969000
1"
#25010000
0"
#25051000
1"
#25092000
0"
#25133000
1"
#25174000
0"
#25215000
1"
#25256000
0"
#25297000
1"
#25338000
0"
#25379000
1"
#25420000
0"
#25461000
1"
#25502000
0"
#25543000
1"
#25584000
0"
#25625000
1"
#25666000
0"
#25707000
1"
#25748000
0"
#25789000
1"
#25830000
0"
#25871000
1"
#25912000
0"
#25953000
1"
#25994000
0"
#26035000
1"
#26076000
0"
#26117000
1"
#26158000
0"
#26199000
1"
#26240000
0"
#26281000
1"
#26322000
0"
#26363000
1"
#26404000
0"
#26445000
1"
#26486000
0"
#26527000
1"
#26568000
0"
#26609000
1"
#26650000
0"
#26691000
1"
#26732000
0"
#26773000
1"
#26814000
0"
#26855000
1"
#26896000
0"
#26937000
1"
#26978000
0"
#27019000
1"
#27060000
0"
#27101000
1"
#27142000
0"
#27183000
1"
#27224000
0"
#27265000
1"
#27306000
0"
#27347000
1"
#27388000
0"
#27429000
1"
#27470000
0"
#27511000
1"
#27552000
0"
#27593000
1"
#27634000
0"
#27675000
1"
#27716000
0"
#27757000
1"
#27798000
0"
#27839000
1"
#27880000
0"
#27921000
1"
#27962000
0"
#28003000
1"
#28044000
0"
#28085000
1"
#28126000
0"
#28167000
1"
#28208000
0"
#28249000
1"
#28290000
0"
#28331000
1"
#28372000
0"
#28413000
1"
#28454000
0"
#28495000
1"
#28536000
0"
#28577000
1"
#28618000
0"
#28659000
1"
#28700000
0"
#28741000
1"
#28782000
0"
#28823000
1"
#28864000
0"
#28905000
1"
#28946000
0"
#28987000
1"
#29028000
0"
#29069000
1"
#29110000
0"
#29151000
1"
#29192000
0"
#29233000
1"
#29274000
0"
#29315000
1"
#29356000
0"
#29397000
1"
#29438000
0"
#29479000
1"
#29520000
0"
#29561000
1"
#29602000
0"
#29643000
1"
#29684000
0"
#29725000
1"
#29766000
0"
#29807000
1"
#29848000
0"
#29889000
1"
#29930000
0"
#29971000
1"
#30012000
0"
#30053000
1"
#30094000
0"
#30135000
1"
#30176000
0"
#30217000
1"
#30258000
0"
#30299000
1"
#30340000
0"
#30381000
1"
#30422000
0"
#30463000
1"
#30504000
0"
#30545000
1"
#30586000
0"
#30627000
1"
#30668000
0"
#30709000
1"
#30750000
0"
#30791000
1"
#30832000
0"
#30873000
1"
#30914000
0"
#30955000
1"
#30996000
0"
#31037000
1"
#31078000
0"
#31119000
1"
#31160000
0"
#31201000
1"
#31242000
0"
#31283000
1"
#31324000
0"
#31365000
1"
#31406000
0"
#31447000
1"
#31488000
0"
#31529000
1"
#31570000
0"
#31611000
1"
#31652000
0"
#31693000
1"
#31734000
0"
#31775000
1"
#31816000
0"
#31857000
1"
#31898000
0"
#31939000
1"
#31980000
0"
#32021000
1"
#32062000
0"
#32103000
1"
#32144000
0"
#32185000
1"
#32226000
0"
#32267000
1"
#32308000
0"
#32349000
1"
#32390000
0"
#32431000
1"
#32472000
0"
#32513000
1"
#32554000
0"
#32595000
1"
#32636000
0"
#32677000
1"
#32718000
0"
#32759000
1"
#32800000
0"
#32841000
1"
#32882000
0"
#32923000
1"
#32964000
0"
#33005000
1"
#33046000
0"
#33087000
1"
#33128000
0"
#33169000
1"
#33210000
0"
#33251000
1"
#33292000
0"
#33333000
1"
#33374000
0"
#33415000
1"
#33456000
0"
#33497000
1"
#33538000
0"
#33579000
1"
#33620000
0"
#33661000
1"
#33702000
0"
#33743000
1"
#33784000
0"
#33825000
1"
#33866000
0"
#33907000
1"
#33948000
0"
#33989000
1"
#34030000
0"
#34071000
1"
#34112000
0"
#34153000
1"
#34194000
0"
#34235000
1"
#34276000
0"
#34317000
1"
#34358000
0"
#34399000
1"
#34440000
0"
#34481000
1"
#34522000
0"
#34563000
1"
#34604000
0"
#34645000
1"
#34686000
0"
#34727000
1"
#34768000
0"
#34809000
1"
#34850000
0"
#34891000
1"
#34932000
0"
#34973000
1"
#35014000
0"
#35055000
1"
#35096000
0"
#35137000
1"
#35178000
0"
#35219000
1"
#35260000
0"
#35301000
1"
#35342000
0"
#35383000
1"
#35424000
0"
#35465000
1"
#35506000
0"
#35547000
1"
#35588000
0"
#35629000
1"
#35670000
0"
#35711000
1"
#35752000
0"
#35793000
1"
#35834000
0"
#35875000
1"
#35916000
0"
#35957000
1"
#35998000
0"
#36039000
1"
#36080000
0"
#36121000
1"
#36162000
0"
#36203000
1"
#36244000
0"
#36285000
1"
#36326000
0"
#36367000
1"
#36408000
0"
#36449000
1"
#36490000
0"
#36531000
1"
#36572000
0"
#36613000
1"
#36654000
0"
#36695000
1"
#36736000
0"
#36777000
1"
#36818000
0"
#36859000
1"
#36900000
0"
#36941000
1"
#36982000
0"
#37023000
1"
#37064000
0"
#37105000
1"
#37146000
0"
#37187000
1"
#37228000
0"
#37269000
1"
#37310000
0"
#37351000
1"
#37392000
0"
#37433000
1"
#37474000
0"
#37515000
1"
#37556000
0"
#37597000
1"
#37638000
0"
#37679000
1"
#37720000
0"
#37761000
1"
#37802000
0"
#37843000
1"
#37884000
0"
#37925000
1"
#37966000
0"
#38007000
1"
#38048000
0"
#38089000
1"
#38130000
0"
#38171000
1"
#38212000
0"
#38253000
1"
#38294000
0"
#38335000
1"
#38376000
0"
#38417000
1"
#38458000
0"
#38499000
1"
#38540000
0"
#38581000
1"
#38622000
0"
#38663000
1"
#38704000
0"
#38745000
1"
#38786000
0"
#38827000
1"
#38868000
0"
#38909000
1"
#38950000
0"
#38991000
1"
#39032000
0"
#39073000
1"
#39114000
0"
#39155000
1"
#39196000
0"
#39237000
1"
#39278000
0"
#39319000
1"
#39360000
0"
#39401000
1"
#39442000
0"
#39483000
1"
#39524000
0"
#39565000
1"
#39606000
0"
#39647000
1"
#39688000
0"
#39729000
1"
#39770000
0"
#39811000
1"
#39852000
0"
#39893000
1"
#39934000
0"
#39975000
1"
#40016000
0"
#40057000
1"
#40098000
0"
#40139000
1"
#40180000
0"
#40221000
1"
#40262000
0"
#40303000
1"
#40344000
0"
#40385000
1"
#40426000
0"
#40467000
1"
#40508000
0"
#40549000
1"
#40590000
0"
#40631000
1"
#40672000
0"
#40713000
1"
#40754000
0"
#40795000
1"
#40836000
0"
#40877000
1"
#40918000
0"
#40959000
1#
1"
#41000000
0"
#41041000
b1010000001010001 &
b111110100 %
1!
b101100001 (
1"
#41082000
0"
#41123000
b101100000 (
1"
#41164000
0"
#41205000
b101011111 (
1"
#41246000
0"
#41287000
b101011110 (
1"
#41328000
0"
#41369000
b101011101 (
1"
#41410000
0"
#41451000
b101011100 (
1"
#41492000
0"
#41533000
b101011011 (
1"
#41574000
0"
#41615000
b101011010 (
1"
#41656000
0"
#41697000
b101011001 (
1"
#41738000
0"
#41779000
b101011000 (
1"
#41820000
0"
#41861000
b101010111 (
1"
#41902000
0"
#41943000
b101010110 (
1"
#41984000
0"
#42025000
b101010101 (
1"
#42066000
0"
#42107000
b101010100 (
1"
#42148000
0"
#42189000
b101010011 (
1"
#42230000
0"
#42271000
b101010010 (
1"
#42312000
0"
#42353000
b101010001 (
1"
#42394000
0"
#42435000
b101010000 (
1"
#42476000
0"
#42517000
b101001111 (
1"
#42558000
0"
#42599000
b101001110 (
1"
#42640000
0"
#42681000
b101001101 (
1"
#42722000
0"
#42763000
b101001100 (
1"
#42804000
0"
#42845000
b101001011 (
1"
#42886000
0"
#42927000
b101001010 (
1"
#42968000
0"
#43009000
b101001001 (
1"
#43050000
0"
#43091000
b101001000 (
1"
#43132000
0"
#43173000
b101000111 (
1"
#43214000
0"
#43255000
b101000110 (
1"
#43296000
0"
#43337000
b101000101 (
1"
#43378000
0"
#43419000
b101000100 (
1"
#43460000
0"
#43501000
b101000011 (
1"
#43542000
0"
#43583000
b101000010 (
1"
#43624000
0"
#43665000
b101000001 (
1"
#43706000
0"
#43747000
b101000000 (
1"
#43788000
0"
#43829000
b100111111 (
1"
#43870000
0"
#43911000
b100111110 (
1"
#43952000
0"
#43993000
b100111101 (
1"
#44034000
0"
#44075000
b100111100 (
1"
#44116000
0"
#44157000
b100111011 (
1"
#44198000
0"
#44239000
b100111010 (
1"
#44280000
0"
#44321000
b100111001 (
1"
#44362000
0"
#44403000
b100111000 (
1"
#44444000
0"
#44485000
b100110111 (
1"
#44526000
0"
#44567000
b100110110 (
1"
#44608000
0"
#44649000
b100110101 (
1"
#44690000
0"
#44731000
b100110100 (
1"
#44772000
0"
#44813000
b100110011 (
1"
#44854000
0"
#44895000
b100110010 (
1"
#44936000
0"
#44977000
b100110001 (
1"
#45018000
0"
#45059000
b100110000 (
1"
#45100000
0"
#45141000
b100101111 (
1"
#45182000
0"
#45223000
b100101110 (
1"
#45264000
0"
#45305000
b100101101 (
1"
#45346000
0"
#45387000
b100101100 (
1"
#45428000
0"
#45469000
b100101011 (
1"
#45510000
0"
#45551000
b100101010 (
1"
#45592000
0"
#45633000
b100101001 (
1"
#45674000
0"
#45715000
b100101000 (
1"
#45756000
0"
#45797000
b100100111 (
1"
#45838000
0"
#45879000
b100100110 (
1"
#45920000
0"
#45961000
b100100101 (
1"
#46002000
0"
#46043000
b100100100 (
1"
#46084000
0"
#46125000
b100100011 (
1"
#46166000
0"
#46207000
b100100010 (
1"
#46248000
0"
#46289000
b100100001 (
1"
#46330000
0"
#46371000
b100100000 (
1"
#46412000
0"
#46453000
b100011111 (
1"
#46494000
0"
#46535000
b100011110 (
1"
#46576000
0"
#46617000
b100011101 (
1"
#46658000
0"
#46699000
b100011100 (
1"
#46740000
0"
#46781000
b100011011 (
1"
#46822000
0"
#46863000
b100011010 (
1"
#46904000
0"
#46945000
b100011001 (
1"
#46986000
0"
#47027000
b100011000 (
1"
#47068000
0"
#47109000
b100010111 (
1"
#47150000
0"
#47191000
b100010110 (
1"
#47232000
0"
#47273000
b100010101 (
1"
#47314000
0"
#47355000
b100010100 (
1"
#47396000
0"
#47437000
b100010011 (
1"
#47478000
0"
#47519000
b100010010 (
1"
#47560000
0"
#47601000
b100010001 (
1"
#47642000
0"
#47683000
b100010000 (
1"
#47724000
0"
#47765000
b100001111 (
1"
#47806000
0"
#47847000
b100001110 (
1"
#47888000
0"
#47929000
b100001101 (
1"
#47970000
0"
#48011000
b100001100 (
1"
#48052000
0"
#48093000
b100001011 (
1"
#48134000
0"
#48175000
b100001010 (
1"
#48216000
0"
#48257000
b100001001 (
1"
#48298000
0"
#48339000
b100001000 (
1"
#48380000
0"
#48421000
b100000111 (
1"
#48462000
0"
#48503000
b100000110 (
1"
#48544000
0"
#48585000
b100000101 (
1"
#48626000
0"
#48667000
b100000100 (
1"
#48708000
0"
#48749000
b100000011 (
1"
#48790000
0"
#48831000
b100000010 (
1"
#48872000
0"
#48913000
b100000001 (
1"
#48954000
0"
#48995000
b100000000 (
1"
#49036000
0"
#49077000
b11111111 (
1"
#49118000
0"
#49159000
b11111110 (
1"
#49200000
0"
#49241000
b11111101 (
1"
#49282000
0"
#49323000
b11111100 (
1"
#49364000
0"
#49405000
b11111011 (
1"
#49446000
0"
#49487000
b11111010 (
1"
#49528000
0"
#49569000
b11111001 (
1"
#49610000
0"
#49651000
b11111000 (
1"
#49692000
0"
#49733000
b11110111 (
1"
#49774000
0"
#49815000
b11110110 (
1"
#49856000
0"
#49897000
b11110101 (
1"
#49938000
0"
#49979000
b11110100 (
1"
#50020000
0"
#50061000
b11110011 (
1"
#50102000
0"
#50143000
b11110010 (
1"
#50184000
0"
#50225000
b11110001 (
1"
#50266000
0"
#50307000
b11110000 (
1"
#50348000
0"
#50389000
b11101111 (
1"
#50430000
0"
#50471000
b11101110 (
1"
#50512000
0"
#50553000
b11101101 (
1"
#50594000
0"
#50635000
b11101100 (
1"
#50676000
0"
#50717000
b11101011 (
1"
#50758000
0"
#50799000
b11101010 (
1"
#50840000
0"
#50881000
b11101001 (
1"
#50922000
0"
#50963000
b11101000 (
1"
#51004000
0"
#51045000
b11100111 (
1"
#51086000
0"
#51127000
b11100110 (
1"
#51168000
0"
#51209000
b11100101 (
1"
#51250000
0"
#51291000
b11100100 (
1"
#51332000
0"
#51373000
b11100011 (
1"
#51414000
0"
#51455000
b11100010 (
1"
#51496000
0"
#51537000
b11100001 (
1"
#51578000
0"
#51619000
b11100000 (
1"
#51660000
0"
#51701000
b11011111 (
1"
#51742000
0"
#51783000
b11011110 (
1"
#51824000
0"
#51865000
b11011101 (
1"
#51906000
0"
#51947000
b11011100 (
1"
#51988000
0"
#52029000
b11011011 (
1"
#52070000
0"
#52111000
b11011010 (
1"
#52152000
0"
#52193000
b11011001 (
1"
#52234000
0"
#52275000
b11011000 (
1"
#52316000
0"
#52357000
b11010111 (
1"
#52398000
0"
#52439000
b11010110 (
1"
#52480000
0"
#52521000
b11010101 (
1"
#52562000
0"
#52603000
b11010100 (
1"
#52644000
0"
#52685000
b11010011 (
1"
#52726000
0"
#52767000
b11010010 (
1"
#52808000
0"
#52849000
b11010001 (
1"
#52890000
0"
#52931000
b11010000 (
1"
#52972000
0"
#53013000
b11001111 (
1"
#53054000
0"
#53095000
b11001110 (
1"
#53136000
0"
#53177000
b11001101 (
1"
#53218000
0"
#53259000
b11001100 (
1"
#53300000
0"
#53341000
b11001011 (
1"
#53382000
0"
#53423000
b11001010 (
1"
#53464000
0"
#53505000
b11001001 (
1"
#53546000
0"
#53587000
b11001000 (
1"
#53628000
0"
#53669000
b11000111 (
1"
#53710000
0"
#53751000
b11000110 (
1"
#53792000
0"
#53833000
b11000101 (
1"
#53874000
0"
#53915000
b11000100 (
1"
#53956000
0"
#53997000
b11000011 (
1"
#54038000
0"
#54079000
b11000010 (
1"
#54120000
0"
#54161000
b11000001 (
1"
#54202000
0"
#54243000
b11000000 (
1"
#54284000
0"
#54325000
b10111111 (
1"
#54366000
0"
#54407000
b10111110 (
1"
#54448000
0"
#54489000
b10111101 (
1"
#54530000
0"
#54571000
b10111100 (
1"
#54612000
0"
#54653000
b10111011 (
1"
#54694000
0"
#54735000
b10111010 (
1"
#54776000
0"
#54817000
b10111001 (
1"
#54858000
0"
#54899000
b10111000 (
1"
#54940000
0"
#54981000
b10110111 (
1"
#55022000
0"
#55063000
b10110110 (
1"
#55104000
0"
#55145000
b10110101 (
1"
#55186000
0"
#55227000
b10110100 (
1"
#55268000
0"
#55309000
b10110011 (
1"
#55350000
0"
#55391000
b10110010 (
1"
#55432000
0"
#55473000
b10110001 (
1"
#55514000
0"
#55555000
b10110000 (
1"
#55596000
0"
#55637000
b10101111 (
1"
#55678000
0"
#55719000
b10101110 (
1"
#55760000
0"
#55801000
b10101101 (
1"
#55842000
0"
#55883000
b10101100 (
1"
#55924000
0"
#55965000
b10101011 (
1"
#56006000
0"
#56047000
b10101010 (
1"
#56088000
0"
#56129000
b10101001 (
1"
#56170000
0"
#56211000
b10101000 (
1"
#56252000
0"
#56293000
b10100111 (
1"
#56334000
0"
#56375000
b10100110 (
1"
#56416000
0"
#56457000
b10100101 (
1"
#56498000
0"
#56539000
b10100100 (
1"
#56580000
0"
#56621000
b10100011 (
1"
#56662000
0"
#56703000
b10100010 (
1"
#56744000
0"
#56785000
b10100001 (
1"
#56826000
0"
#56867000
b10100000 (
1"
#56908000
0"
#56949000
b10011111 (
1"
#56990000
0"
#57031000
b10011110 (
1"
#57072000
0"
#57113000
b10011101 (
1"
#57154000
0"
#57195000
b10011100 (
1"
#57236000
0"
#57277000
b10011011 (
1"
#57318000
0"
#57359000
b10011010 (
1"
#57400000
0"
#57441000
b10011001 (
1"
#57482000
0"
#57523000
b10011000 (
1"
#57564000
0"
#57605000
b10010111 (
1"
#57646000
0"
#57687000
b10010110 (
1"
#57728000
0"
#57769000
b10010101 (
1"
#57810000
0"
#57851000
b10010100 (
1"
#57892000
0"
#57933000
b10010011 (
1"
#57974000
0"
#58015000
b10010010 (
1"
#58056000
0"
#58097000
b10010001 (
1"
#58138000
0"
#58179000
b10010000 (
1"
#58220000
0"
#58261000
b10001111 (
1"
#58302000
0"
#58343000
b10001110 (
1"
#58384000
0"
#58425000
b10001101 (
1"
#58466000
0"
#58507000
b10001100 (
1"
#58548000
0"
#58589000
b10001011 (
1"
#58630000
0"
#58671000
b10001010 (
1"
#58712000
0"
#58753000
b10001001 (
1"
#58794000
0"
#58835000
b10001000 (
1"
#58876000
0"
#58917000
b10000111 (
1"
#58958000
0"
