rtl/bird_deterrent_pwm.v
// Ultrasonic PWM generator for bird deterrence
//
// tone_val is a half-period divisor:
//   tone_val = 333 → half-period = 333 cycles @ 12MHz → full period = 666 → ~18kHz (max, safe ceiling)
//   tone_val = 353 → half-period = 353 cycles @ 12MHz → full period = 706 → ~17kHz (min)
//
// When enable=0, speaker_out is held low (silent).
// When enable=1, speaker_out toggles at the rate set by tone_val.
module bird_deterrent_pwm (
    input            clk,
    input  [15:0]    tone_val,
    input            enable,
    output reg       speaker_out
);
    reg [15:0] counter;

    always @(posedge clk) begin
        if (!enable) begin
            counter     <= 16'd0;
            speaker_out <= 1'b0;
        end else begin
            if (counter == 16'd0) begin
                counter     <= tone_val;   // reload
                speaker_out <= ~speaker_out; // toggle = one half-cycle done
            end else begin
                counter <= counter - 1'b1;
            end
        end
    end
endmodule

rtl/prng.v
// 16-bit Fibonacci LFSR pseudo-random number generator
// Polynomial: x^16 + x^14 + x^13 + x^11 + 1
// Feedback taps: bits 15, 13, 12, 10 (0-indexed from LSB)
// Advances by 1 step each time 'advance' is pulsed (tied to 1Hz tick)
// Used to jitter the deterrent frequency so birds don't habituate
module prng (
    input  clk,
    input  rst_n,
    input  advance,
    output [15:0] lfsr_out
);
    reg [15:0] lfsr;

    // XOR feedback from taps
    wire feedback = lfsr[15] ^ lfsr[13] ^ lfsr[12] ^ lfsr[10];

    always @(posedge clk or negedge rst_n) begin
        if (!rst_n)
            lfsr <= 16'hACE1; // non-zero seed — any non-zero value works
        else if (advance)
            lfsr <= {lfsr[14:0], feedback};
    end

    assign lfsr_out = lfsr;
endmodule

rtl/heartbeat.v
// 1Hz tick generator
// 12MHz clock / 12,000,000 cycles = 1 pulse per second
// tick is high for exactly 1 clock cycle each second
module heartbeat (
    input  clk,
    input  rst_n,
    output reg tick
);
    reg [23:0] counter;

    always @(posedge clk or negedge rst_n) begin
        if (!rst_n) begin
            counter <= 24'd0;
            tick    <= 1'b0;
        end else if (counter == 24'd11_999_999) begin
            counter <= 24'd0;
            tick    <= 1'b1;
        end else begin
            counter <= counter + 1'b1;
            tick    <= 1'b0;
        end
    end
endmodule

rtl/sonic_shield_top.v
// Sonic Shield — Core Logic Module
//
// Takes clk as an explicit input so testbenches can drive it directly.
// Synthesis wrapper (sonic_shield_board.v) provides clk from SB_HFOSC.
//
// SHADOW_MODE parameter:
//   0 = Active  — speaker fires when sensor triggers (field deployment)
//   1 = Silent  — sensors log activity but speaker stays off (first 3 days)
//
// Detection: deterrent_en = mic_in OR pir_in
//   Either sensor independently triggers the deterrent.
//
// Frequency sweep:
//   tone_val = 333 + (lfsr % 21) → sweeps 18kHz down to ~17kHz
//   Changes every 1Hz tick so birds cannot habituate to a fixed frequency.
module sonic_shield_top #(
    parameter SHADOW_MODE = 0
) (
    input  clk,
    input  rst_n,
    input  mic_in,       // High when mic comparator detects bird-frequency sound
    input  pir_in,       // High when PIR detects movement
    output speaker_out,  // PWM to transistor driver → master node piezo
    output rf_tx,        // 433MHz trigger to satellite nodes (HIGH = deterrent active)
    output status_led,   // 1Hz heartbeat — goes to SB_RGBA_DRV in board wrapper
    output uart_tx       // Serial telemetry (stub — idle high until Phase 4)
);
    wire        tick_1hz;
    wire [15:0] lfsr;
    wire [15:0] tone_val;
    wire        pwm_out;
    reg         deterrent_en;

    // --- Heartbeat: 1Hz tick drives all 1-second state changes ---
    heartbeat hb_inst (
        .clk   (clk),
        .rst_n (rst_n),
        .tick  (tick_1hz)
    );

    // --- PRNG: advances 1 step per second, produces jitter for tone_val ---
    prng prng_inst (
        .clk      (clk),
        .rst_n    (rst_n),
        .advance  (tick_1hz),
        .lfsr_out (lfsr)
    );

    // tone_val sweeps 333–353 (18kHz to ~17kHz ceiling, safe for neighbors)
    // lfsr % 21 maps 16-bit value to 0–20 range
    assign tone_val = 16'd333 + (lfsr % 16'd21);

    // --- Detection: either sensor fires the deterrent ---
    always @(posedge clk or negedge rst_n) begin
        if (!rst_n)
            deterrent_en <= 1'b0;
        else
            deterrent_en <= mic_in | pir_in;
    end

    // --- PWM generator ---
    bird_deterrent_pwm pwm_inst (
        .clk        (clk),
        .tone_val   (tone_val),
        .enable     (deterrent_en),
        .speaker_out(pwm_out)
    );

    // SHADOW_MODE gates both the local speaker and the RF trigger
    assign speaker_out = (SHADOW_MODE == 1) ? 1'b0 : pwm_out;

    // rf_tx: sends a simple HIGH/LOW trigger to 433MHz transmitter (FS1000A DATA pin)
    // Satellite nodes receive this, gate their local 555-timer oscillator → piezo
    // We send deterrent_en (not the PWM) — 433MHz modules can't carry 18kHz OOK
    assign rf_tx = (SHADOW_MODE == 1) ? 1'b0 : deterrent_en;

    // Heartbeat tick drives the LED blink (1Hz)
    assign status_led = tick_1hz;

    // UART idle high — Phase 4 will replace this with real telemetry
    assign uart_tx = 1'b1;

endmodule

sim/tb_sonic_shield_top.v
// Testbench: sonic_shield_top
//
// What this tests:
//   1. speaker_out silent when both sensors idle
//   2. speaker_out active when mic_in=1 (acoustic trigger)
//   3. speaker_out active when pir_in=1 (motion trigger)
//   4. SHADOW_MODE=1 blocks speaker even when sensors fire
//
// We instantiate sonic_shield_top directly (not the board wrapper)
// so we can drive clk ourselves — no SB_HFOSC needed in simulation.
//
// Run: make sim_top (from sim/ directory)
// View: gtkwave tb_sonic_shield_top.vcd
`timescale 1ns/1ps

module tb_sonic_shield_top;

    reg  clk;
    reg  rst_n;
    reg  mic_in;
    reg  pir_in;
    wire speaker_out;
    wire status_led;
    wire uart_tx_wire;

    // 12MHz: ~83ns period
    initial clk = 0;
    always #41 clk = ~clk;

    // --- DUT: Active mode (SHADOW_MODE=0) ---
    sonic_shield_top #(.SHADOW_MODE(0)) dut_active (
        .clk        (clk),
        .rst_n      (rst_n),
        .mic_in     (mic_in),
        .pir_in     (pir_in),
        .speaker_out(speaker_out),
        .status_led (status_led),
        .uart_tx    (uart_tx_wire)
    );

    // --- Shadow mode DUT wired to separate outputs ---
    wire shadow_speaker;
    wire shadow_led;
    wire shadow_uart;

    sonic_shield_top #(.SHADOW_MODE(1)) dut_shadow (
        .clk        (clk),
        .rst_n      (rst_n),
        .mic_in     (mic_in),
        .pir_in     (pir_in),
        .speaker_out(shadow_speaker),
        .status_led (shadow_led),
        .uart_tx    (shadow_uart)
    );

    // Helper task: wait N cycles then sample
    task wait_cycles;
        input integer n;
        repeat(n) @(posedge clk);
    endtask

    integer saw_toggle;

    initial begin
        $dumpfile("tb_sonic_shield_top.vcd");
        $dumpvars(0, tb_sonic_shield_top);

        // Reset
        rst_n  = 0;
        mic_in = 0;
        pir_in = 0;
        wait_cycles(10);
        rst_n = 1;
        wait_cycles(5);

        // --- Test 1: Both sensors idle — speaker must be silent ---
        wait_cycles(1000);
        if (speaker_out !== 1'b0)
            $display("FAIL Test1: speaker active with no sensor input");
        else
            $display("PASS Test1: speaker silent — no sensors triggered");

        // --- Test 2: mic_in trigger — speaker must activate ---
        mic_in = 1;
        wait_cycles(800); // deterrent_en registers after 1 clock, PWM starts
        saw_toggle = 0;

        // Sample speaker_out for 1000 cycles and check it toggles
        begin : check_pwm
            integer k;
            for (k = 0; k < 1000; k = k + 1) begin
                @(posedge clk);
                if (speaker_out === 1'b1) saw_toggle = 1;
            end
        end

        if (!saw_toggle)
            $display("FAIL Test2: speaker never went high on mic_in trigger");
        else
            $display("PASS Test2: speaker active on mic_in trigger");

        mic_in = 0;
        wait_cycles(10);

        // --- Test 3: pir_in trigger ---
        pir_in = 1;
        wait_cycles(800);
        saw_toggle = 0;

        begin : check_pir
            integer j;
            for (j = 0; j < 1000; j = j + 1) begin
                @(posedge clk);
                if (speaker_out === 1'b1) saw_toggle = 1;
            end
        end

        if (!saw_toggle)
            $display("FAIL Test3: speaker never went high on pir_in trigger");
        else
            $display("PASS Test3: speaker active on pir_in trigger");

        pir_in = 0;
        wait_cycles(10);

        // --- Test 4: SHADOW_MODE=1 blocks speaker ---
        mic_in = 1;
        wait_cycles(800);

        if (shadow_speaker !== 1'b0)
            $display("FAIL Test4: SHADOW_MODE did not block speaker output");
        else
            $display("PASS Test4: SHADOW_MODE correctly silences speaker");

        mic_in = 0;

        // --- Test 5: UART TX stays idle high ---
        if (uart_tx_wire !== 1'b1)
            $display("FAIL Test5: UART TX not idle high");
        else
            $display("PASS Test5: UART TX idle high (stub)");

        $display("--- Simulation complete ---");
        $finish;
    end

endmodule

sim/tb_sonic_shield_top.vcd
$date
	Tue Apr 28 22:35:47 2026
$end
$version
	Icarus Verilog
$end
$timescale
	1ps
$end
$scope module tb_sonic_shield_top $end
$var wire 1 ! shadow_speaker $end
$var wire 1 " shadow_uart $end
$var wire 1 # uart_tx_wire $end
$var wire 1 $ status_led $end
$var wire 1 % speaker_out $end
$var wire 1 & shadow_led $end
$var reg 1 ' clk $end
$var reg 1 ( mic_in $end
$var reg 1 ) pir_in $end
$var reg 1 * rst_n $end
$var integer 32 + saw_toggle [31:0] $end
$scope module dut_active $end
$var wire 1 ' clk $end
$var wire 1 ( mic_in $end
$var wire 1 ) pir_in $end
$var wire 1 , rf_tx $end
$var wire 1 * rst_n $end
$var wire 1 % speaker_out $end
$var wire 1 $ status_led $end
$var wire 1 # uart_tx $end
$var wire 16 - tone_val [15:0] $end
$var wire 1 . tick_1hz $end
$var wire 1 / pwm_out $end
$var wire 16 0 lfsr [15:0] $end
$var reg 1 1 deterrent_en $end
$scope module hb_inst $end
$var wire 1 ' clk $end
$var wire 1 * rst_n $end
$var reg 24 2 counter [23:0] $end
$var reg 1 . tick $end
$upscope $end
$scope module prng_inst $end
$var wire 1 . advance $end
$var wire 1 ' clk $end
$var wire 1 3 feedback $end
$var wire 16 4 lfsr_out [15:0] $end
$var wire 1 * rst_n $end
$var reg 16 5 lfsr [15:0] $end
$upscope $end
$scope module pwm_inst $end
$var wire 1 ' clk $end
$var wire 1 1 enable $end
$var wire 16 6 tone_val [15:0] $end
$var reg 16 7 counter [15:0] $end
$var reg 1 / speaker_out $end
$upscope $end
$upscope $end
$scope module dut_shadow $end
$var wire 1 ' clk $end
$var wire 1 ( mic_in $end
$var wire 1 ) pir_in $end
$var wire 1 8 rf_tx $end
$var wire 1 * rst_n $end
$var wire 1 ! speaker_out $end
$var wire 1 & status_led $end
$var wire 1 " uart_tx $end
$var wire 16 9 tone_val [15:0] $end
$var wire 1 : tick_1hz $end
$var wire 1 ; pwm_out $end
$var wire 16 < lfsr [15:0] $end
$var reg 1 = deterrent_en $end
$scope module hb_inst $end
$var wire 1 ' clk $end
$var wire 1 * rst_n $end
$var reg 24 > counter [23:0] $end
$var reg 1 : tick $end
$upscope $end
$scope module prng_inst $end
$var wire 1 : advance $end
$var wire 1 ' clk $end
$var wire 1 ? feedback $end
$var wire 16 @ lfsr_out [15:0] $end
$var wire 1 * rst_n $end
$var reg 16 A lfsr [15:0] $end
$upscope $end
$scope module pwm_inst $end
$var wire 1 ' clk $end
$var wire 1 = enable $end
$var wire 16 B tone_val [15:0] $end
$var reg 16 C counter [15:0] $end
$var reg 1 ; speaker_out $end
$upscope $end
$upscope $end
$scope begin check_pir $end
$var integer 32 D j [31:0] $end
$upscope $end
$scope begin check_pwm $end
$var integer 32 E k [31:0] $end
$upscope $end
$scope task wait_cycles $end
$var integer 32 F n [31:0] $end
$upscope $end
$upscope $end
$enddefinitions $end
#0
$dumpvars
b1010 F
bx E
bx D
bx C
b101010111 B
b1010110011100001 A
b1010110011100001 @
1?
b0 >
0=
b1010110011100001 <
x;
0:
b101010111 9
08
bx 7
b101010111 6
b1010110011100001 5
b1010110011100001 4
13
b0 2
01
b1010110011100001 0
x/
0.
b101010111 -
0,
bx +
0*
0)
0(
0'
0&
x%
0$
1#
1"
0!
$end
#41000
0%
0/
b0 7
0;
b0 C
1'
#82000
0'
#123000
1'
#164000
0'
#205000
1'
#246000
0'
#287000
1'
#328000
0'
#369000
1'
#410000
0'
#451000
1'
#492000
0'
#533000
1'
#574000
0'
#615000
1'
#656000
0'
#697000
1'
#738000
0'
#779000
b1 2
b1 >
b101 F
1*
1'
#820000
0'
#861000
b10 >
b10 2
1'
#902000
0'
#943000
b11 2
b11 >
1'
#984000
0'
#1025000
b100 >
b100 2
1'
#1066000
0'
#1107000
b101 2
b101 >
1'
#1148000
0'
#1189000
b110 >
b110 2
b1111101000 F
1'
#1230000
0'
#1271000
b111 2
b111 >
1'
#1312000
0'
#1353000
b1000 >
b1000 2
1'
#1394000
0'
#1435000
b1001 2
b1001 >
1'
#1476000
0'
#1517000
b1010 >
b1010 2
1'
#1558000
0'
#1599000
b1011 2
b1011 >
1'
#1640000
0'
#1681000
b1100 >
b1100 2
1'
#1722000
0'
#1763000
b1101 2
b1101 >
1'
#1804000
0'
#1845000
b1110 >
b1110 2
1'
#1886000
0'
#1927000
b1111 2
b1111 >
1'
#1968000
0'
#2009000
b10000 >
b10000 2
1'
#2050000
0'
#2091000
b10001 2
b10001 >
1'
#2132000
0'
#2173000
b10010 >
b10010 2
1'
#2214000
0'
#2255000
b10011 2
b10011 >
1'
#2296000
0'
#2337000
b10100 >
b10100 2
1'
#2378000
0'
#2419000
b10101 2
b10101 >
1'
#2460000
0'
#2501000
b10110 >
b10110 2
1'
#2542000
0'
#2583000
b10111 2
b10111 >
1'
#2624000
0'
#2665000
b11000 >
b11000 2
1'
#2706000
0'
#2747000
b11001 2
b11001 >
1'
#2788000
0'
#2829000
b11010 >
b11010 2
1'
#2870000
0'
#2911000
b11011 2
b11011 >
1'
#2952000
0'
#2993000
b11100 >
b11100 2
1'
#3034000
0'
#3075000
b11101 2
b11101 >
1'
#3116000
0'
#3157000
b11110 >
b11110 2
1'
#3198000
0'
#3239000
b11111 2
b11111 >
1'
#3280000
0'
#3321000
b100000 >
b100000 2
1'
#3362000
0'
#3403000
b100001 2
b100001 >
1'
#3444000
0'
#3485000
b100010 >
b100010 2
1'
#3526000
0'
#3567000
b100011 2
b100011 >
1'
#3608000
0'
#3649000
b100100 >
b100100 2
1'
#3690000
0'
#3731000
b100101 2
b100101 >
1'
#3772000
0'
#3813000
b100110 >
b100110 2
1'
#3854000
0'
#3895000
b100111 2
b100111 >
1'
#3936000
0'
#3977000
b101000 >
b101000 2
1'
#4018000
0'
#4059000
b101001 2
b101001 >
1'
#4100000
0'
#4141000
b101010 >
b101010 2
1'
#4182000
0'
#4223000
b101011 2
b101011 >
1'
#4264000
0'
#4305000
b101100 >
b101100 2
1'
#4346000
0'
#4387000
b101101 2
b101101 >
1'
#4428000
0'
#4469000
b101110 >
b101110 2
1'
#4510000
0'
#4551000
b101111 2
b101111 >
1'
#4592000
0'
#4633000
b110000 >
b110000 2
1'
#4674000
0'
#4715000
b110001 2
b110001 >
1'
#4756000
0'
#4797000
b110010 >
b110010 2
1'
#4838000
0'
#4879000
b110011 2
b110011 >
1'
#4920000
0'
#4961000
b110100 >
b110100 2
1'
#5002000
0'
#5043000
b110101 2
b110101 >
1'
#5084000
0'
#5125000
b110110 >
b110110 2
1'
#5166000
0'
#5207000
b110111 2
b110111 >
1'
#5248000
0'
#5289000
b111000 >
b111000 2
1'
#5330000
0'
#5371000
b111001 2
b111001 >
1'
#5412000
0'
#5453000
b111010 >
b111010 2
1'
#5494000
0'
#5535000
b111011 2
b111011 >
1'
#5576000
0'
#5617000
b111100 >
b111100 2
1'
#5658000
0'
#5699000
b111101 2
b111101 >
1'
#5740000
0'
#5781000
b111110 >
b111110 2
1'
#5822000
0'
#5863000
b111111 2
b111111 >
1'
#5904000
0'
#5945000
b1000000 >
b1000000 2
1'
#5986000
0'
#6027000
b1000001 2
b1000001 >
1'
#6068000
0'
#6109000
b1000010 >
b1000010 2
1'
#6150000
0'
#6191000
b1000011 2
b1000011 >
1'
#6232000
0'
#6273000
b1000100 >
b1000100 2
1'
#6314000
0'
#6355000
b1000101 2
b1000101 >
1'
#6396000
0'
#6437000
b1000110 >
b1000110 2
1'
#6478000
0'
#6519000
b1000111 2
b1000111 >
1'
#6560000
0'
#6601000
b1001000 >
b1001000 2
1'
#6642000
0'
#6683000
b1001001 2
b1001001 >
1'
#6724000
0'
#6765000
b1001010 >
b1001010 2
1'
#6806000
0'
#6847000
b1001011 2
b1001011 >
1'
#6888000
0'
#6929000
b1001100 >
b1001100 2
1'
#6970000
0'
#7011000
b1001101 2
b1001101 >
1'
#7052000
0'
#7093000
b1001110 >
b1001110 2
1'
#7134000
0'
#7175000
b1001111 2
b1001111 >
1'
#7216000
0'
#7257000
b1010000 >
b1010000 2
1'
#7298000
0'
#7339000
b1010001 2
b1010001 >
1'
#7380000
0'
#7421000
b1010010 >
b1010010 2
1'
#7462000
0'
#7503000
b1010011 2
b1010011 >
1'
#7544000
0'
#7585000
b1010100 >
b1010100 2
1'
#7626000
0'
#7667000
b1010101 2
b1010101 >
1'
#7708000
0'
#7749000
b1010110 >
b1010110 2
1'
#7790000
0'
#7831000
b1010111 2
b1010111 >
1'
#7872000
0'
#7913000
b1011000 >
b1011000 2
1'
#7954000
0'
#7995000
b1011001 2
b1011001 >
1'
#8036000
0'
#8077000
b1011010 >
b1011010 2
1'
#8118000
0'
#8159000
b1011011 2
b1011011 >
1'
#8200000
0'
#8241000
b1011100 >
b1011100 2
1'
#8282000
0'
#8323000
b1011101 2
b1011101 >
1'
#8364000
0'
#8405000
b1011110 >
b1011110 2
1'
#8446000
0'
#8487000
b1011111 2
b1011111 >
1'
#8528000
0'
#8569000
b1100000 >
b1100000 2
1'
#8610000
0'
#8651000
b1100001 2
b1100001 >
1'
#8692000
0'
#8733000
b1100010 >
b1100010 2
1'
#8774000
0'
#8815000
b1100011 2
b1100011 >
1'
#8856000
0'
#8897000
b1100100 >
b1100100 2
1'
#8938000
0'
#8979000
b1100101 2
b1100101 >
1'
#9020000
0'
#9061000
b1100110 >
b1100110 2
1'
#9102000
0'
#9143000
b1100111 2
b1100111 >
1'
#9184000
0'
#9225000
b1101000 >
b1101000 2
1'
#9266000
0'
#9307000
b1101001 2
b1101001 >
1'
#9348000
0'
#9389000
b1101010 >
b1101010 2
1'
#9430000
0'
#9471000
b1101011 2
b1101011 >
1'
#9512000
0'
#9553000
b1101100 >
b1101100 2
1'
#9594000
0'
#9635000
b1101101 2
b1101101 >
1'
#9676000
0'
#9717000
b1101110 >
b1101110 2
1'
#9758000
0'
#9799000
b1101111 2
b1101111 >
1'
#9840000
0'
#9881000
b1110000 >
b1110000 2
1'
#9922000
0'
#9963000
b1110001 2
b1110001 >
1'
#10004000
0'
#10045000
b1110010 >
b1110010 2
1'
#10086000
0'
#10127000
b1110011 2
b1110011 >
1'
#10168000
0'
#10209000
b1110100 >
b1110100 2
1'
#10250000
0'
#10291000
b1110101 2
b1110101 >
1'
#10332000
0'
#10373000
b1110110 >
b1110110 2
1'
#10414000
0'
#10455000
b1110111 2
b1110111 >
1'
#10496000
0'
#10537000
b1111000 >
b1111000 2
1'
#10578000
0'
#10619000
b1111001 2
b1111001 >
1'
#10660000
0'
#10701000
b1111010 >
b1111010 2
1'
#10742000
0'
#10783000
b1111011 2
b1111011 >
1'
#10824000
0'
#10865000
b1111100 >
b1111100 2
1'
#10906000
0'
#10947000
b1111101 2
b1111101 >
1'
#10988000
0'
#11029000
b1111110 >
b1111110 2
1'
#11070000
0'
#11111000
b1111111 2
b1111111 >
1'
#11152000
0'
#11193000
b10000000 >
b10000000 2
1'
#11234000
0'
#11275000
b10000001 2
b10000001 >
1'
#11316000
0'
#11357000
b10000010 >
b10000010 2
1'
#11398000
0'
#11439000
b10000011 2
b10000011 >
1'
#11480000
0'
#11521000
b10000100 >
b10000100 2
1'
#11562000
0'
#11603000
b10000101 2
b10000101 >
1'
#11644000
0'
#11685000
b10000110 >
b10000110 2
1'
#11726000
0'
#11767000
b10000111 2
b10000111 >
1'
#11808000
0'
#11849000
b10001000 >
b10001000 2
1'
#11890000
0'
#11931000
b10001001 2
b10001001 >
1'
#11972000
0'
#12013000
b10001010 >
b10001010 2
1'
#12054000
0'
#12095000
b10001011 2
b10001011 >
1'
#12136000
0'
#12177000
b10001100 >
b10001100 2
1'
#12218000
0'
#12259000
b10001101 2
b10001101 >
1'
#12300000
0'
#12341000
b10001110 >
b10001110 2
1'
#12382000
0'
#12423000
b10001111 2
b10001111 >
1'
#12464000
0'
#12505000
b10010000 >
b10010000 2
1'
#12546000
0'
#12587000
b10010001 2
b10010001 >
1'
#12628000
0'
#12669000
b10010010 >
b10010010 2
1'
#12710000
0'
#12751000
b10010011 2
b10010011 >
1'
#12792000
0'
#12833000
b10010100 >
b10010100 2
1'
#12874000
0'
#12915000
b10010101 2
b10010101 >
1'
#12956000
0'
#12997000
b10010110 >
b10010110 2
1'
#13038000
0'
#13079000
b10010111 2
b10010111 >
1'
#13120000
0'
#13161000
b10011000 >
b10011000 2
1'
#13202000
0'
#13243000
b10011001 2
b10011001 >
1'
#13284000
0'
#13325000
b10011010 >
b10011010 2
1'
#13366000
0'
#13407000
b10011011 2
b10011011 >
1'
#13448000
0'
#13489000
b10011100 >
b10011100 2
1'
#13530000
0'
#13571000
b10011101 2
b10011101 >
1'
#13612000
0'
#13653000
b10011110 >
b10011110 2
1'
#13694000
0'
#13735000
b10011111 2
b10011111 >
1'
#13776000
0'
#13817000
b10100000 >
b10100000 2
1'
#13858000
0'
#13899000
b10100001 2
b10100001 >
1'
#13940000
0'
#13981000
b10100010 >
b10100010 2
1'
#14022000
0'
#14063000
b10100011 2
b10100011 >
1'
#14104000
0'
#14145000
b10100100 >
b10100100 2
1'
#14186000
0'
#14227000
b10100101 2
b10100101 >
1'
#14268000
0'
#14309000
b10100110 >
b10100110 2
1'
#14350000
0'
#14391000
b10100111 2
b10100111 >
1'
#14432000
0'
#14473000
b10101000 >
b10101000 2
1'
#14514000
0'
#14555000
b10101001 2
b10101001 >
1'
#14596000
0'
#14637000
b10101010 >
b10101010 2
1'
#14678000
0'
#14719000
b10101011 2
b10101011 >
1'
#14760000
0'
#14801000
b10101100 >
b10101100 2
1'
#14842000
0'
#14883000
b10101101 2
b10101101 >
1'
#14924000
0'
#14965000
b10101110 >
b10101110 2
1'
#15006000
0'
#15047000
b10101111 2
b10101111 >
1'
#15088000
0'
#15129000
b10110000 >
b10110000 2
1'
#15170000
0'
#15211000
b10110001 2
b10110001 >
1'
#15252000
0'
#15293000
b10110010 >
b10110010 2
1'
#15334000
0'
#15375000
b10110011 2
b10110011 >
1'
#15416000
0'
#15457000
b10110100 >
b10110100 2
1'
#15498000
0'
#15539000
b10110101 2
b10110101 >
1'
#15580000
0'
#15621000
b10110110 >
b10110110 2
1'
#15662000
0'
#15703000
b10110111 2
b10110111 >
1'
#15744000
0'
#15785000
b10111000 >
b10111000 2
1'
#15826000
0'
#15867000
b10111001 2
b10111001 >
1'
#15908000
0'
#15949000
b10111010 >
b10111010 2
1'
#15990000
0'
#16031000
b10111011 2
b10111011 >
1'
#16072000
0'
#16113000
b10111100 >
b10111100 2
1'
#16154000
0'
#16195000
b10111101 2
b10111101 >
1'
#16236000
0'
#16277000
b10111110 >
b10111110 2
1'
#16318000
0'
#16359000
b10111111 2
b10111111 >
1'
#16400000
0'
#16441000
b11000000 >
b11000000 2
1'
#16482000
0'
#16523000
b11000001 2
b11000001 >
1'
#16564000
0'
#16605000
b11000010 >
b11000010 2
1'
#16646000
0'
#16687000
b11000011 2
b11000011 >
1'
#16728000
0'
#16769000
b11000100 >
b11000100 2
1'
#16810000
0'
#16851000
b11000101 2
b11000101 >
1'
#16892000
0'
#16933000
b11000110 >
b11000110 2
1'
#16974000
0'
#17015000
b11000111 2
b11000111 >
1'
#17056000
0'
#17097000
b11001000 >
b11001000 2
1'
#17138000
0'
#17179000
b11001001 2
b11001001 >
1'
#17220000
0'
#17261000
b11001010 >
b11001010 2
1'
#17302000
0'
#17343000
b11001011 2
b11001011 >
1'
#17384000
0'
#17425000
b11001100 >
b11001100 2
1'
#17466000
0'
#17507000
b11001101 2
b11001101 >
1'
#17548000
0'
#17589000
b11001110 >
b11001110 2
1'
#17630000
0'
#17671000
b11001111 2
b11001111 >
1'
#17712000
0'
#17753000
b11010000 >
b11010000 2
1'
#17794000
0'
#17835000
b11010001 2
b11010001 >
1'
#17876000
0'
#17917000
b11010010 >
b11010010 2
1'
#17958000
0'
#17999000
b11010011 2
b11010011 >
1'
#18040000
0'
#18081000
b11010100 >
b11010100 2
1'
#18122000
0'
#18163000
b11010101 2
b11010101 >
1'
#18204000
0'
#18245000
b11010110 >
b11010110 2
1'
#18286000
0'
#18327000
b11010111 2
b11010111 >
1'
#18368000
0'
#18409000
b11011000 >
b11011000 2
1'
#18450000
0'
#18491000
b11011001 2
b11011001 >
1'
#18532000
0'
#18573000
b11011010 >
b11011010 2
1'
#18614000
0'
#18655000
b11011011 2
b11011011 >
1'
#18696000
0'
#18737000
b11011100 >
b11011100 2
1'
#18778000
0'
#18819000
b11011101 2
b11011101 >
1'
#18860000
0'
#18901000
b11011110 >
b11011110 2
1'
#18942000
0'
#18983000
b11011111 2
b11011111 >
1'
#19024000
0'
#19065000
b11100000 >
b11100000 2
1'
#19106000
0'
#19147000
b11100001 2
b11100001 >
1'
#19188000
0'
#19229000
b11100010 >
b11100010 2
1'
#19270000
0'
#19311000
b11100011 2
b11100011 >
1'
#19352000
0'
#19393000
b11100100 >
b11100100 2
1'
#19434000
0'
#19475000
b11100101 2
b11100101 >
1'
#19516000
0'
#19557000
b11100110 >
b11100110 2
1'
#19598000
0'
#19639000
b11100111 2
b11100111 >
1'
#19680000
0'
#19721000
b11101000 >
b11101000 2
1'
#19762000
0'
#19803000
b11101001 2
b11101001 >
1'
#19844000
0'
#19885000
b11101010 >
b11101010 2
1'
#19926000
0'
#19967000
b11101011 2
b11101011 >
1'
#20008000
0'
#20049000
b11101100 >
b11101100 2
1'
#20090000
0'
#20131000
b11101101 2
b11101101 >
1'
#20172000
0'
#20213000
b11101110 >
b11101110 2
1'
#20254000
0'
#20295000
b11101111 2
b11101111 >
1'
#20336000
0'
#20377000
b11110000 >
b11110000 2
1'
#20418000
0'
#20459000
b11110001 2
b11110001 >
1'
#20500000
0'
#20541000
b11110010 >
b11110010 2
1'
#20582000
0'
#20623000
b11110011 2
b11110011 >
1'
#20664000
0'
#20705000
b11110100 >
b11110100 2
1'
#20746000
0'
#20787000
b11110101 2
b11110101 >
1'
#20828000
0'
#20869000
b11110110 >
b11110110 2
1'
#20910000
0'
#20951000
b11110111 2
b11110111 >
1'
#20992000
0'
#21033000
b11111000 >
b11111000 2
1'
#21074000
0'
#21115000
b11111001 2
b11111001 >
1'
#21156000
0'
#21197000
b11111010 >
b11111010 2
1'
#21238000
0'
#21279000
b11111011 2
b11111011 >
1'
#21320000
0'
#21361000
b11111100 >
b11111100 2
1'
#21402000
0'
#21443000
b11111101 2
b11111101 >
1'
#21484000
0'
#21525000
b11111110 >
b11111110 2
1'
#21566000
0'
#21607000
b11111111 2
b11111111 >
1'
#21648000
0'
#21689000
b100000000 >
b100000000 2
1'
#21730000
0'
#21771000
b100000001 2
b100000001 >
1'
#21812000
0'
#21853000
b100000010 >
b100000010 2
1'
#21894000
0'
#21935000
b100000011 2
b100000011 >
1'
#21976000
0'
#22017000
b100000100 >
b100000100 2
1'
#22058000
0'
#22099000
b100000101 2
b100000101 >
1'
#22140000
0'
#22181000
b100000110 >
b100000110 2
1'
#22222000
0'
#22263000
b100000111 2
b100000111 >
1'
#22304000
0'
#22345000
b100001000 >
b100001000 2
1'
#22386000
0'
#22427000
b100001001 2
b100001001 >
1'
#22468000
0'
#22509000
b100001010 >
b100001010 2
1'
#22550000
0'
#22591000
b100001011 2
b100001011 >
1'
#22632000
0'
#22673000
b100001100 >
b100001100 2
1'
#22714000
0'
#22755000
b100001101 2
b100001101 >
1'
#22796000
0'
#22837000
b100001110 >
b100001110 2
1'
#22878000
0'
#22919000
b100001111 2
b100001111 >
1'
#22960000
0'
#23001000
b100010000 >
b100010000 2
1'
#23042000
0'
#23083000
b100010001 2
b100010001 >
1'
#23124000
0'
#23165000
b100010010 >
b100010010 2
1'
#23206000
0'
#23247000
b100010011 2
b100010011 >
1'
#23288000
0'
#23329000
b100010100 >
b100010100 2
1'
#23370000
0'
#23411000
b100010101 2
b100010101 >
1'
#23452000
0'
#23493000
b100010110 >
b100010110 2
1'
#23534000
0'
#23575000
b100010111 2
b100010111 >
1'
#23616000
0'
#23657000
b100011000 >
b100011000 2
1'
#23698000
0'
#23739000
b100011001 2
b100011001 >
1'
#23780000
0'
#23821000
b100011010 >
b100011010 2
1'
#23862000
0'
#23903000
b100011011 2
b100011011 >
1'
#23944000
0'
#23985000
b100011100 >
b100011100 2
1'
#24026000
0'
#24067000
b100011101 2
b100011101 >
1'
#24108000
0'
#24149000
b100011110 >
b100011110 2
1'
#24190000
0'
#24231000
b100011111 2
b100011111 >
1'
#24272000
0'
#24313000
b100100000 >
b100100000 2
1'
#24354000
0'
#24395000
b100100001 2
b100100001 >
1'
#24436000
0'
#24477000
b100100010 >
b100100010 2
1'
#24518000
0'
#24559000
b100100011 2
b100100011 >
1'
#24600000
0'
#24641000
b100100100 >
b100100100 2
1'
#24682000
0'
#24723000
b100100101 2
b100100101 >
1'
#24764000
0'
#24805000
b100100110 >
b100100110 2
1'
#24846000
0'
#24887000
b100100111 2
b100100111 >
1'
#24928000
0'
#24969000
b100101000 >
b100101000 2
1'
#25010000
0'
#25051000
b100101001 2
b100101001 >
1'
#25092000
0'
#25133000
b100101010 >
b100101010 2
1'
#25174000
0'
#25215000
b100101011 2
b100101011 >
1'
#25256000
0'
#25297000
b100101100 >
b100101100 2
1'
#25338000
0'
#25379000
b100101101 2
b100101101 >
1'
#25420000
0'
#25461000
b100101110 >
b100101110 2
1'
#25502000
0'
